odoo/addons/purchase_order_product_recommendation_xlsx/README.rst
odoo/addons/purchase_order_product_recommendation_xlsx/__init__.py
odoo/addons/purchase_order_product_recommendation_xlsx/__manifest__.py
odoo/addons/purchase_order_product_recommendation_xlsx/i18n/es.po
odoo/addons/purchase_order_product_recommendation_xlsx/i18n/purchase_order_product_recommendation_xlsx.pot
odoo/addons/purchase_order_product_recommendation_xlsx/readme/CONTRIBUTORS.rst
odoo/addons/purchase_order_product_recommendation_xlsx/readme/DESCRIPTION.rst
odoo/addons/purchase_order_product_recommendation_xlsx/readme/USAGE.rst
odoo/addons/purchase_order_product_recommendation_xlsx/report/__init__.py
odoo/addons/purchase_order_product_recommendation_xlsx/report/recommendation_xlsx.py
odoo/addons/purchase_order_product_recommendation_xlsx/report/recommendation_xlsx.xml
odoo/addons/purchase_order_product_recommendation_xlsx/static/description/icon.png
odoo/addons/purchase_order_product_recommendation_xlsx/static/description/index.html
odoo/addons/purchase_order_product_recommendation_xlsx/tests/__init__.py
odoo/addons/purchase_order_product_recommendation_xlsx/tests/test_recommendation.py
odoo/addons/purchase_order_product_recommendation_xlsx/wizards/__init__.py
odoo/addons/purchase_order_product_recommendation_xlsx/wizards/purchase_order_recommendation.py
odoo/addons/purchase_order_product_recommendation_xlsx/wizards/purchase_order_recommendation_view.xml
odoo13_addon_purchase_order_product_recommendation_xlsx-13.0.1.0.1.dev5.dist-info/METADATA
odoo13_addon_purchase_order_product_recommendation_xlsx-13.0.1.0.1.dev5.dist-info/WHEEL
odoo13_addon_purchase_order_product_recommendation_xlsx-13.0.1.0.1.dev5.dist-info/top_level.txt
odoo13_addon_purchase_order_product_recommendation_xlsx-13.0.1.0.1.dev5.dist-info/RECORD
